odoo/addons/partner_contact_show_ref/README.rst
odoo/addons/partner_contact_show_ref/__init__.py
odoo/addons/partner_contact_show_ref/__manifest__.py
odoo/addons/partner_contact_show_ref/models/__init__.py
odoo/addons/partner_contact_show_ref/models/res_partner.py
odoo/addons/partner_contact_show_ref/readme/CONTRIBUTORS.md
odoo/addons/partner_contact_show_ref/readme/DESCRIPTION.md
odoo/addons/partner_contact_show_ref/readme/USAGE.md
odoo/addons/partner_contact_show_ref/static/description/icon.png
odoo/addons/partner_contact_show_ref/static/description/index.html
odoo/addons/partner_contact_show_ref/tests/__init__.py
odoo/addons/partner_contact_show_ref/tests/test_partner_contact_show_ref.py
odoo/addons/partner_contact_show_ref/views/res_partner_views.xml
odoo_addon_partner_contact_show_ref-17.0.1.1.0.dist-info/METADATA
odoo_addon_partner_contact_show_ref-17.0.1.1.0.dist-info/WHEEL
odoo_addon_partner_contact_show_ref-17.0.1.1.0.dist-info/top_level.txt
odoo_addon_partner_contact_show_ref-17.0.1.1.0.dist-info/RECORD
